LICENSE
MANIFEST.in
README.rst
setup.cfg
setup.py
django_timeseries.egg-info/PKG-INFO
django_timeseries.egg-info/SOURCES.txt
django_timeseries.egg-info/dependency_links.txt
django_timeseries.egg-info/requires.txt
django_timeseries.egg-info/top_level.txt
timeseries/__init__.py
timeseries/utils.py