Metadata-Version: 1.1
Name: django-timeseries
Version: 1.0.1
Summary: `timeseries` is a set of django application tools designed to facilitate the collation and maintenance of timeseries data.
Home-page: https://github.com/anthonyalmarza/timeseries
Author: Anthony Almarza
Author-email: UNKNOWN
License: UNKNOWN
Keywords: timeseries,django,data,latest
Platform: UNKNOWN
Classifier: Intended Audience :: Developers
Classifier: Natural Language :: English
Classifier: Operating System :: OS Independent
Classifier: Programming Language :: Python
